lex_bot_tester/__init__.py
lex_bot_tester/aws/__init__.py
lex_bot_tester/aws/alexa/__init__.py
lex_bot_tester/aws/alexa/alexaskillmanagementclient.py
lex_bot_tester/aws/alexa/alexaskilltest.py
lex_bot_tester/aws/alexa/alexatestbuilder.py
lex_bot_tester/aws/lex/__init__.py
lex_bot_tester/aws/lex/conversation.py
lex_bot_tester/aws/lex/lexbottest.py
lex_bot_tester/aws/lex/lexmodelsclient.py
lex_bot_tester/aws/lex/lexruntimeclient.py
lex_bot_tester/aws/lex/resultbase.py
lex_bot_tester/aws/polly/__init__.py
lex_bot_tester/aws/polly/pollyclient.py
lex_bot_tester/util/__init__.py
lex_bot_tester/util/color.py
lex_bot_tester/util/conversion.py
lex_bot_tester-1.0.6.data/scripts/urutu
lex_bot_tester-1.0.6.dist-info/DESCRIPTION.rst
lex_bot_tester-1.0.6.dist-info/METADATA
lex_bot_tester-1.0.6.dist-info/RECORD
lex_bot_tester-1.0.6.dist-info/WHEEL
lex_bot_tester-1.0.6.dist-info/metadata.json
lex_bot_tester-1.0.6.dist-info/top_level.txt
