Metadata-Version: 2.0
Name: lex-bot-tester
Version: 1.0.6
Summary: lex-bot-tester is a library that simplifies the creation of Amazon Alexa Skills and AWS Lex Bot tests.
Home-page: https://github.com/dtmilano/lex-bot-tester/
Author: Diego Torres Milano
Author-email: dtmilano@gmail.com
License: GPL-3.0
Keywords: amazon aws lex bot tester conversation test automation
Platform: UNKNOWN
Classifier: Development Status :: 5 - Production/Stable
Classifier: Intended Audience :: Developers
Classifier: Topic :: Software Development :: Build Tools
Classifier: License :: OSI Approved :: GNU General Public License v3 (GPLv3)
Classifier: Programming Language :: Python :: 2
Classifier: Programming Language :: Python :: 2.6
Classifier: Programming Language :: Python :: 2.7
Classifier: Programming Language :: Python :: 3
Classifier: Programming Language :: Python :: 3.2
Classifier: Programming Language :: Python :: 3.3
Classifier: Programming Language :: Python :: 3.4
Requires-Dist: boto3
Requires-Dist: requests
Requires-Dist: setuptools
Requires-Dist: six
